<?xml version="1.0" encoding="UTF-8"?>
<TestCase name="ProjectTest">
<Environment>
    <QtVersion>5.7.0</QtVersion>
    <QtBuild>Qt 5.7.0 (x86_64&#x002D;little_endian&#x002D;llp64 shared (dynamic) debug build; by MSVC 2013)</QtBuild>
    <QTestVersion>5.7.0</QTestVersion>
</Environment>
<TestFunction name="initTestCase">
<Incident type="pass" file="" line="0" />
    <Duration msecs="1.392668"/>
</TestFunction>
<TestFunction name="Insert_Unique_ElementType_Positive">
<Message type="qdebug" file="" line="0">
    <Description><![CDATA[Delete  RW::SQL::Project(0x25dc50)]]></Description>
</Message>
<Message type="info" file="c:\projekte\remoterepros\remoteutil\remotedataconnectlibrary\unittestremotedataconnectlibrary\generatedfiles\debug\../../ProjectTest.h" line="44">
    <Description><![CDATA[QVERIFY(m_Repository->InsertProject(tp))]]></Description>
</Message>
<Message type="qdebug" file="" line="0">
    <Description><![CDATA[Delete  RW::SQL::Project(0x25dbf8)]]></Description>
</Message>
<Message type="qdebug" file="" line="0">
    <Description><![CDATA[Delete  RW::SQL::Project(0x25dd08)]]></Description>
</Message>
<Message type="info" file="c:\projekte\remoterepros\remoteutil\remotedataconnectlibrary\unittestremotedataconnectlibrary\generatedfiles\debug\../../ProjectTest.h" line="47">
    <Description><![CDATA[QVERIFY(m_Repository->GetProjectByID(1, ret))]]></Description>
</Message>
<Message type="info" file="c:\projekte\remoterepros\remoteutil\remotedataconnectlibrary\unittestremotedataconnectlibrary\generatedfiles\debug\../../ProjectTest.h" line="48">
    <Description><![CDATA[QVERIFY(ret.Projectname() == BR213IC_HL_MY16)]]></Description>
</Message>
<Message type="qdebug" file="" line="0">
    <Description><![CDATA[Delete  RW::SQL::Project(0x25dc50)]]></Description>
</Message>
<Message type="info" file="c:\projekte\remoterepros\remoteutil\remotedataconnectlibrary\unittestremotedataconnectlibrary\generatedfiles\debug\../../ProjectTest.h" line="52">
    <Description><![CDATA[QVERIFY(m_Repository->InsertProject(t))]]></Description>
</Message>
<Message type="qdebug" file="" line="0">
    <Description><![CDATA[Delete  RW::SQL::Project(0x25dc50)]]></Description>
</Message>
<Message type="info" file="c:\projekte\remoterepros\remoteutil\remotedataconnectlibrary\unittestremotedataconnectlibrary\generatedfiles\debug\../../ProjectTest.h" line="55">
    <Description><![CDATA[QVERIFY(m_Repository->InsertProject(t))]]></Description>
</Message>
<Message type="qdebug" file="" line="0">
    <Description><![CDATA[Delete  RW::SQL::Project(0x25dc50)]]></Description>
</Message>
<Message type="info" file="c:\projekte\remoterepros\remoteutil\remotedataconnectlibrary\unittestremotedataconnectlibrary\generatedfiles\debug\../../ProjectTest.h" line="58">
    <Description><![CDATA[QVERIFY(m_Repository->InsertProject(t))]]></Description>
</Message>
<Message type="qdebug" file="" line="0">
    <Description><![CDATA[Delete  RW::SQL::Project(0x25dc50)]]></Description>
</Message>
<Message type="info" file="c:\projekte\remoterepros\remoteutil\remotedataconnectlibrary\unittestremotedataconnectlibrary\generatedfiles\debug\../../ProjectTest.h" line="61">
    <Description><![CDATA[QVERIFY(m_Repository->InsertProject(t))]]></Description>
</Message>
<Message type="qdebug" file="" line="0">
    <Description><![CDATA[Delete  RW::SQL::Project(0x25dc50)]]></Description>
</Message>
<Message type="info" file="c:\projekte\remoterepros\remoteutil\remotedataconnectlibrary\unittestremotedataconnectlibrary\generatedfiles\debug\../../ProjectTest.h" line="64">
    <Description><![CDATA[QVERIFY(m_Repository->InsertProject(t))]]></Description>
</Message>
<Message type="qdebug" file="" line="0">
    <Description><![CDATA[Delete  RW::SQL::Project(0x25dc50)]]></Description>
</Message>
<Message type="info" file="c:\projekte\remoterepros\remoteutil\remotedataconnectlibrary\unittestremotedataconnectlibrary\generatedfiles\debug\../../ProjectTest.h" line="67">
    <Description><![CDATA[QVERIFY(m_Repository->InsertProject(t))]]></Description>
</Message>
<Message type="qdebug" file="" line="0">
    <Description><![CDATA[Delete  RW::SQL::Project(0x25dc50)]]></Description>
</Message>
<Message type="info" file="c:\projekte\remoterepros\remoteutil\remotedataconnectlibrary\unittestremotedataconnectlibrary\generatedfiles\debug\../../ProjectTest.h" line="70">
    <Description><![CDATA[QVERIFY(m_Repository->InsertProject(t))]]></Description>
</Message>
<Message type="qdebug" file="" line="0">
    <Description><![CDATA[Delete  RW::SQL::Project(0x25dc50)]]></Description>
</Message>
<Message type="info" file="c:\projekte\remoterepros\remoteutil\remotedataconnectlibrary\unittestremotedataconnectlibrary\generatedfiles\debug\../../ProjectTest.h" line="73">
    <Description><![CDATA[QVERIFY(m_Repository->InsertProject(t))]]></Description>
</Message>
<Message type="qdebug" file="" line="0">
    <Description><![CDATA[Delete  RW::SQL::Project(0x25dc50)]]></Description>
</Message>
<Message type="info" file="c:\projekte\remoterepros\remoteutil\remotedataconnectlibrary\unittestremotedataconnectlibrary\generatedfiles\debug\../../ProjectTest.h" line="76">
    <Description><![CDATA[QVERIFY(m_Repository->InsertProject(t))]]></Description>
</Message>
<Message type="qdebug" file="" line="0">
    <Description><![CDATA[Delete  RW::SQL::Project(0x25dc50)]]></Description>
</Message>
<Message type="info" file="c:\projekte\remoterepros\remoteutil\remotedataconnectlibrary\unittestremotedataconnectlibrary\generatedfiles\debug\../../ProjectTest.h" line="79">
    <Description><![CDATA[QVERIFY(m_Repository->InsertProject(t))]]></Description>
</Message>
<Message type="qdebug" file="" line="0">
    <Description><![CDATA[Delete  RW::SQL::Project(0x25dc50)]]></Description>
</Message>
<Message type="info" file="c:\projekte\remoterepros\remoteutil\remotedataconnectlibrary\unittestremotedataconnectlibrary\generatedfiles\debug\../../ProjectTest.h" line="82">
    <Description><![CDATA[QVERIFY(m_Repository->InsertProject(t))]]></Description>
</Message>
<Message type="qdebug" file="" line="0">
    <Description><![CDATA[Delete  RW::SQL::Project(0x25dc50)]]></Description>
</Message>
<Message type="info" file="c:\projekte\remoterepros\remoteutil\remotedataconnectlibrary\unittestremotedataconnectlibrary\generatedfiles\debug\../../ProjectTest.h" line="85">
    <Description><![CDATA[QVERIFY(m_Repository->InsertProject(t))]]></Description>
</Message>
<Message type="qdebug" file="" line="0">
    <Description><![CDATA[Delete  RW::SQL::Project(0x25dc50)]]></Description>
</Message>
<Message type="info" file="c:\projekte\remoterepros\remoteutil\remotedataconnectlibrary\unittestremotedataconnectlibrary\generatedfiles\debug\../../ProjectTest.h" line="88">
    <Description><![CDATA[QVERIFY(m_Repository->InsertProject(t))]]></Description>
</Message>
<Message type="qdebug" file="" line="0">
    <Description><![CDATA[Delete  RW::SQL::Project(0x25dc50)]]></Description>
</Message>
<Message type="info" file="c:\projekte\remoterepros\remoteutil\remotedataconnectlibrary\unittestremotedataconnectlibrary\generatedfiles\debug\../../ProjectTest.h" line="91">
    <Description><![CDATA[QVERIFY(m_Repository->InsertProject(t))]]></Description>
</Message>
<Message type="qdebug" file="" line="0">
    <Description><![CDATA[Delete  RW::SQL::Project(0x25dd78)]]></Description>
</Message>
<Message type="qdebug" file="" line="0">
    <Description><![CDATA[Delete  RW::SQL::Project(0x25ddc0)]]></Description>
</Message>
<Message type="qdebug" file="" line="0">
    <Description><![CDATA[Delete  RW::SQL::Project(0x25dda0)]]></Description>
</Message>
<Incident type="pass" file="" line="0" />
    <Duration msecs="1110.234153"/>
</TestFunction>
<TestFunction name="GetAllProjects_Positiv">
<Message type="qdebug" file="" line="0">
    <Description><![CDATA[Delete  RW::SQL::Project(0x25dd88)]]></Description>
</Message>
<Message type="qdebug" file="" line="0">
    <Description><![CDATA[Delete  RW::SQL::Project(0x25dd88)]]></Description>
</Message>
<Message type="qdebug" file="" line="0">
    <Description><![CDATA[Delete  RW::SQL::Project(0x25dd88)]]></Description>
</Message>
<Message type="qdebug" file="" line="0">
    <Description><![CDATA[Delete  RW::SQL::Project(0x25dd88)]]></Description>
</Message>
<Message type="qdebug" file="" line="0">
    <Description><![CDATA[Delete  RW::SQL::Project(0x25dd88)]]></Description>
</Message>
<Message type="qdebug" file="" line="0">
    <Description><![CDATA[Delete  RW::SQL::Project(0x25dd88)]]></Description>
</Message>
<Message type="qdebug" file="" line="0">
    <Description><![CDATA[Delete  RW::SQL::Project(0x25dd88)]]></Description>
</Message>
<Message type="qdebug" file="" line="0">
    <Description><![CDATA[Delete  RW::SQL::Project(0x25dd88)]]></Description>
</Message>
<Message type="qdebug" file="" line="0">
    <Description><![CDATA[Delete  RW::SQL::Project(0x25dd88)]]></Description>
</Message>
<Message type="qdebug" file="" line="0">
    <Description><![CDATA[Delete  RW::SQL::Project(0x25dd88)]]></Description>
</Message>
<Message type="qdebug" file="" line="0">
    <Description><![CDATA[Delete  RW::SQL::Project(0x25dd88)]]></Description>
</Message>
<Message type="qdebug" file="" line="0">
    <Description><![CDATA[Delete  RW::SQL::Project(0x25dd88)]]></Description>
</Message>
<Message type="qdebug" file="" line="0">
    <Description><![CDATA[Delete  RW::SQL::Project(0x25dd88)]]></Description>
</Message>
<Message type="qdebug" file="" line="0">
    <Description><![CDATA[Delete  RW::SQL::Project(0x25dd88)]]></Description>
</Message>
<Message type="qdebug" file="" line="0">
    <Description><![CDATA[Delete  RW::SQL::Project(0x25dd88)]]></Description>
</Message>
<Message type="info" file="c:\projekte\remoterepros\remoteutil\remotedataconnectlibrary\unittestremotedataconnectlibrary\generatedfiles\debug\../../ProjectTest.h" line="97">
    <Description><![CDATA[QVERIFY(m_Repository->GetAllProject(p))]]></Description>
</Message>
<Message type="qdebug" file="" line="0">
    <Description><![CDATA["BR205IC"]]></Description>
</Message>
<Message type="qdebug" file="" line="0">
    <Description><![CDATA[Delete  RW::SQL::Project(0x35e9f0)]]></Description>
</Message>
<Message type="qdebug" file="" line="0">
    <Description><![CDATA[Delete  RW::SQL::Project(0x35e470)]]></Description>
</Message>
<Message type="qdebug" file="" line="0">
    <Description><![CDATA[Delete  RW::SQL::Project(0x35df00)]]></Description>
</Message>
<Message type="qdebug" file="" line="0">
    <Description><![CDATA[Delete  RW::SQL::Project(0x35d980)]]></Description>
</Message>
<Message type="qdebug" file="" line="0">
    <Description><![CDATA[Delete  RW::SQL::Project(0x35d400)]]></Description>
</Message>
<Message type="qdebug" file="" line="0">
    <Description><![CDATA[Delete  RW::SQL::Project(0x35ce90)]]></Description>
</Message>
<Message type="qdebug" file="" line="0">
    <Description><![CDATA[Delete  RW::SQL::Project(0x35c920)]]></Description>
</Message>
<Message type="qdebug" file="" line="0">
    <Description><![CDATA[Delete  RW::SQL::Project(0x35c3a0)]]></Description>
</Message>
<Message type="qdebug" file="" line="0">
    <Description><![CDATA[Delete  RW::SQL::Project(0x35bdc0)]]></Description>
</Message>
<Message type="qdebug" file="" line="0">
    <Description><![CDATA[Delete  RW::SQL::Project(0x35b840)]]></Description>
</Message>
<Message type="qdebug" file="" line="0">
    <Description><![CDATA[Delete  RW::SQL::Project(0x35b2b0)]]></Description>
</Message>
<Message type="qdebug" file="" line="0">
    <Description><![CDATA[Delete  RW::SQL::Project(0x35ad30)]]></Description>
</Message>
<Message type="qdebug" file="" line="0">
    <Description><![CDATA[Delete  RW::SQL::Project(0x353b40)]]></Description>
</Message>
<Message type="qdebug" file="" line="0">
    <Description><![CDATA[Delete  RW::SQL::Project(0x35a210)]]></Description>
</Message>
<Message type="qdebug" file="" line="0">
    <Description><![CDATA[Delete  RW::SQL::Project(0x353c60)]]></Description>
</Message>
<Incident type="pass" file="" line="0" />
    <Duration msecs="3.371887"/>
</TestFunction>
<TestFunction name="Insert_Unique_ElementType_Negative">
<Incident type="pass" file="" line="0" />
    <Duration msecs="0.034832"/>
</TestFunction>
<TestFunction name="cleanupTestCase">
<Incident type="pass" file="" line="0" />
    <Duration msecs="0.027057"/>
</TestFunction>
<Duration msecs="1115.499734"/>
</TestCase>
